{
    "title": "Confidence Intervals",
    "description": "Confidence intervals are a range of values used to estimate the true value of a population parameter. They provide an interval within which we can be certain, to a specified level of confidence (usually 95%), that the true parameter lies. The width of the interval depends on the sample size and variability in the data.",
    "topics": [
        "Definition of Confidence Intervals",
        "Calculating Confidence Intervals",
        "Interpreting Confidence Intervals",
        "Applications of Confidence Intervals"
    ],
    "externalLinks": [
        "https://www.youtube.com/watch?v=tFWsuO9f74o"
    ],
    "memoryTricks": [
        {
            "content": "CI (Confidence Intervals)",
            "type": "acronyms"
        },
        {
            "content": "Confidence intervals give us a range, like a safety net, to catch the true value.",
            "type": "association"
        },
        {
            "content": "Confidence Interval Song: 'Estimate with confidence, find the range, it's common sense!'",
            "type": "songOrRhymes"
        }
    ],
    "mindMaps": [
        {
            "name": "Confidence Intervals",
            "caption": "Understanding Confidence Intervals",
            "rootNode": {
                "name": "Confidence Intervals",
                "description": "A range of values used to estimate the true value of a population parameter.",
                "image": "https://picsum.photos/seed/ConfidenceIntervals/200/300",
                "excerpt": "Understanding Confidence Intervals.",
                "children": [
                    {
                        "name": "Definition",
                        "children": []
                    },
                    {
                        "name": "Calculation",
                        "children": []
                    },
                    {
                        "name": "Interpretation",
                        "children": []
                    },
                    {
                        "name": "Applications",
                        "children": []
                    }
                ]
            }
        }
    ]
}